njab/__init__.py
njab/io/__init__.py
njab/pandas/__init__.py
njab/plotting/__init__.py
njab/plotting/km.py
njab/plotting/lifelines.py
njab/plotting/metrics.py
njab/sklearn/__init__.py
njab/sklearn/pca.py
njab/sklearn/preprocessing.py
njab/sklearn/scoring.py
njab/sklearn/types.py
njab/stats/__init__.py
njab/stats/ancova.py
njab/stats/groups_comparision.py
njab-0.0.3.dist-info/LICENSE
njab-0.0.3.dist-info/METADATA
njab-0.0.3.dist-info/WHEEL
njab-0.0.3.dist-info/top_level.txt
njab-0.0.3.dist-info/RECORD
