Metadata-Version: 2.1
Name: njab
Version: 0.0.3
Summary: not Just Another Biomarker
Author: Henry Webel
Author-email: "Henry Webel" <henry.webel@cpr.ku.dk>
License: MIT
Classifier: License :: OSI Approved :: MIT License
Classifier: Intended Audience :: Healthcare Industry
Classifier: Intended Audience :: Science/Research
Classifier: Programming Language :: Python :: 3
Classifier: Topic :: Scientific/Engineering :: Bio-Informatics
License-File: LICENSE
Requires-Dist: omegaconf
Requires-Dist: lifelines
Requires-Dist: numpy
Requires-Dist: pandas
Requires-Dist: scikit-learn
Requires-Dist: statsmodels
Requires-Dist: umap-learn
Requires-Dist: matplotlib
Requires-Dist: mrmr-selection
Requires-Dist: pingouin
Requires-Dist: seaborn
Provides-Extra: docs
Requires-Dist: sphinx ; extra == 'docs'
Requires-Dist: sphinx-book-theme ; extra == 'docs'
Requires-Dist: myst-nb ; extra == 'docs'
Requires-Dist: ipywidgets ; extra == 'docs'
